hmcli/__init__.py
hmcli/__main__.py
hmcli/utils.py
hmcli/crypto/__init__.py
hmcli/crypto/__main__.py
hmcli/handlers/__init__.py
hmcli/handlers/__main__.py
hmcli/hashing/__init__.py
hmcli/hashing/__main__.py
hmcli/scanners/__init__.py
hmcli/scanners/__main__.py
hmcli-0.10.18.dist-info/DESCRIPTION.rst
hmcli-0.10.18.dist-info/METADATA
hmcli-0.10.18.dist-info/RECORD
hmcli-0.10.18.dist-info/WHEEL
hmcli-0.10.18.dist-info/metadata.json
hmcli-0.10.18.dist-info/top_level.txt
